{
  "description": "项目配置文件",
  "packOptions": {
    "ignore": []
  },
  "setting": {
    "urlCheck": true,
    "es6": true,
    "enhance": false,
    "postcss": true,
    "preloadBackgroundData": false,
    "minified": true,
    "newFeature": false,
    "coverView": true,
    "nodeModules": false,
    "autoAudits": false,
    "showShadowRootInWxmlPanel": true,
    "scopeDataCheck": false,
    "uglifyFileName": false,
    "checkInvalidKey": true,
    "checkSiteMap": true,
    "uploadWithSourceMap": true,
    "compileHotReLoad": false,
    "useMultiFrameRuntime": false,
    "useApiHook": true,
    "babelSetting": {
      "ignore": [],
      "disablePlugins": [],
      "outputPath": ""
    },
    "enableEngineNative": false,
    "useIsolateContext": true,
    "useCompilerModule": true,
    "userConfirmedUseCompilerModuleSwitch": false,
    "packNpmManually": false,
    "packNpmRelationList": [],
    "minifyWXSS": true
  },
  "compileType": "miniprogram",
  "libVersion": "2.13.2",
  "appid": "wx24202ce8fc8142fd",
  "projectname": "live-shop-wechat",
  "debugOptions": {
    "hidedInDevtools": []
  },
  "scripts": {},
  "isGameTourist": false,
  "simulatorType": "wechat",
  "simulatorPluginLibVersion": {},
  "condition": {
    "plugin": {
      "list": []
    },
    "game": {
      "list": []
    },
    "gamePlugin": {
      "list": []
    },
    "miniprogram": {
      "list": [
        {
          "name": "pages/order/submit",
          "pathName": "pages/order/submit",
          "query": "",
          "scene": null
        },
        {
          "name": "首页",
          "pathName": "pages/index/index",
          "query": "",
          "scene": null
        },
        {
          "name": "直播",
          "pathName": "pages/live/live",
          "query": "",
          "scene": null
        },
        {
          "name": "订单",
          "pathName": "pages/order/index",
          "query": "",
          "scene": null
        },
        {
          "name": "首页-分享",
          "pathName": "pages/index/index",
          "query": "invite_id=1",
          "scene": 1007
        },
        {
          "name": "我的",
          "pathName": "pages/user/index",
          "query": "invite_id=1",
          "scene": null
        },
        {
          "name": "关于我们",
          "pathName": "pages/about/index",
          "query": "",
          "scene": null
        }
      ]
    }
  }
}